emojex/__init__.py
emojex/main.py
emojex-0.0.9.dist-info/DESCRIPTION.rst
emojex-0.0.9.dist-info/METADATA
emojex-0.0.9.dist-info/RECORD
emojex-0.0.9.dist-info/WHEEL
emojex-0.0.9.dist-info/metadata.json
emojex-0.0.9.dist-info/top_level.txt
