Metadata-Version: 2.0
Name: emojex
Version: 0.0.9
Summary: Smart converter of popular culture texts to emoji
Home-page: UNKNOWN
Author: 360macky (Marcelo Arias)
Author-email: <mail.marcelo.as@gmail.com>
License: UNKNOWN
Keywords: python,emoji,openai,gpt-3,converter,text
Platform: UNKNOWN
Classifier: Development Status :: 1 - Planning
Classifier: Intended Audience :: Developers
Classifier: Programming Language :: Python :: 3
Classifier: Operating System :: Unix
Classifier: Operating System :: MacOS :: MacOS X
Classifier: Operating System :: Microsoft :: Windows
Requires-Dist: openai
